{
  "Button": {
    "variant": {
      "type": "| \"reset\"\n  | \"primary\"\n  | \"primary_icon\"\n  | \"secondary\"\n  | \"secondary_icon\"\n  | \"destructive\"\n  | \"destructive_icon\"\n  | \"destructive_link\"\n  | \"destructive_secondary\"\n  | \"link\"\n  | \"inverse_link\"\n  | \"inverse\"",
      "defaultValue": "'primary'",
      "required": true,
      "externalProp": false,
      "description": "The different appearance variants for a button. [Avoid using link variants when possible.](https://paste.twilio.design/components/button#button-vs-anchor-link)"
    },
    "as": {
      "type": "keyof IntrinsicElements",
      "defaultValue": "'button'",
      "required": false,
      "externalProp": false,
      "description": "The HTML tag to replace the default `<button>` tag."
    },
    "disabled": {
      "type": "boolean",
      "defaultValue": false,
      "required": false,
      "externalProp": false,
      "description": "Prevent actions from firing on this Button"
    },
    "element": {
      "type": "any",
      "defaultValue": "'BUTTON'",
      "required": false,
      "externalProp": false,
      "description": "Overrides the default element name to apply unique styles with the Customization Provider."
    },
    "fullWidth": {
      "type": "boolean",
      "defaultValue": false,
      "required": false,
      "externalProp": false,
      "description": "Sets the Button width to 100% of the parent container."
    },
    "href": {
      "type": "string",
      "defaultValue": "null",
      "required": false,
      "externalProp": false,
      "description": "A URL to route to. Must use as=\"a\" for this prop to work."
    },
    "i18nExternalLinkLabel": {
      "type": "string",
      "defaultValue": "'(link takes you to an external page)'",
      "required": false,
      "externalProp": false,
      "description": "Title for showExternal icon"
    },
    "loading": {
      "type": "boolean",
      "defaultValue": false,
      "required": false,
      "externalProp": false,
      "description": "Prevent actions and show a loading spinner"
    },
    "pressed": {
      "type": "boolean",
      "defaultValue": false,
      "required": false,
      "externalProp": false,
      "description": "Sets the aria-pressed attribute. Must be used with 'secondary' or 'secondary_icon' variants."
    },
    "size": {
      "type": "ButtonSizes",
      "defaultValue": "'default'",
      "required": false,
      "externalProp": false
    },
    "tabIndex": {
      "type": "ButtonTabIndexes",
      "defaultValue": null,
      "required": false,
      "externalProp": false
    },
    "target": {
      "type": "string",
      "defaultValue": null,
      "required": false,
      "externalProp": false
    },
    "type": {
      "type": "ButtonTypes",
      "defaultValue": "'button'",
      "required": false,
      "externalProp": false,
      "description": "Use at least one `submit` button per `<form>`. Outside of forms use `button` (default)."
    }
  }
}
